examples/analog_input.py
examples/blink.py
examples/dht.py
examples/digital_input.py
examples/fade_wifi.py
examples/hc-sr04_distance_sensor.py
examples/i2c_adxl345_accelerometer.py
examples/imu.py
examples/loop_back.py
examples/microphone.py
examples/neopixel_fireworks.py
examples/rgb_blink.py
examples/rgb_fade.py
examples/servo.py
examples/spi_mpu9250.py
tmx_nano2040_wifi_aio/__init__.py
tmx_nano2040_wifi_aio/private_constants.py
tmx_nano2040_wifi_aio/telemetrix_aio_socket.py
tmx_nano2040_wifi_aio/tmx_nano2040_wifi_aio.py
venv/bin/activate_this.py
tmx_nano_2040_wifi_aio-1.2.2.dist-info/METADATA
tmx_nano_2040_wifi_aio-1.2.2.dist-info/WHEEL
tmx_nano_2040_wifi_aio-1.2.2.dist-info/top_level.txt
tmx_nano_2040_wifi_aio-1.2.2.dist-info/RECORD
