Metadata-Version: 2.4
Name: tmx-nano-2040-wifi-aio
Version: 1.2.2
Summary: Telemetrix Client For The Arduino Nano RP2040 Connect
Author-email: Alan Yorinks <MisterYsLab@gmail.com>
License: AGPL-3.0-or-later
Project-URL: Homepage, https://github.com/MrYsLab/tmx-nano-2040-wifi-aio?tab=readme-ov-file
Project-URL: Issues, https://github.com/MrYsLab/tmx-nano-2040-wifi-aio/issues
Keywords: telemetrix,Arduino,Nano,RP2040,Python,asyncio
Classifier: Development Status :: 5 - Production/Stable
Classifier: Environment :: Other Environment
Classifier: Intended Audience :: Developers
Classifier: Intended Audience :: Education
Classifier: Operating System :: OS Independent
Classifier: Topic :: Software Development :: Libraries :: Python Modules
Requires-Python: >=3.8
Requires-Dist: pyserial
